Java8JianmingJiaocheng/README.md
Java8JianmingJiaocheng/__init__.py
Java8JianmingJiaocheng/__main__.py
Java8JianmingJiaocheng/file.epub
Java8JianmingJiaocheng/index.html
Java8JianmingJiaocheng/css/__init__.py
Java8JianmingJiaocheng/css/annotations.css
Java8JianmingJiaocheng/css/main.css
Java8JianmingJiaocheng/css/normalize.css
Java8JianmingJiaocheng/css/popup.css
Java8JianmingJiaocheng/font/__init__.py
Java8JianmingJiaocheng/font/fontello.eot
Java8JianmingJiaocheng/font/fontello.svg
Java8JianmingJiaocheng/font/fontello.ttf
Java8JianmingJiaocheng/font/fontello.woff
Java8JianmingJiaocheng/img/__init__.py
Java8JianmingJiaocheng/img/annotator-glyph-sprite.png
Java8JianmingJiaocheng/img/annotator-icon-sprite.png
Java8JianmingJiaocheng/img/apple-touch-icon.png
Java8JianmingJiaocheng/img/cancelfullscreen.png
Java8JianmingJiaocheng/img/close.png
Java8JianmingJiaocheng/img/fullscreen.png
Java8JianmingJiaocheng/img/loader.gif
Java8JianmingJiaocheng/img/menu-icon.png
Java8JianmingJiaocheng/img/save.png
Java8JianmingJiaocheng/img/saved.png
Java8JianmingJiaocheng/img/settings-s.png
Java8JianmingJiaocheng/img/settings.png
Java8JianmingJiaocheng/img/star.png
Java8JianmingJiaocheng/js/__init__.py
Java8JianmingJiaocheng/js/epub.js
Java8JianmingJiaocheng/js/epub.min.js
Java8JianmingJiaocheng/js/epub.min.map
Java8JianmingJiaocheng/js/hooks.min.js
Java8JianmingJiaocheng/js/hooks.min.map
Java8JianmingJiaocheng/js/reader.js
Java8JianmingJiaocheng/js/reader.js.map
Java8JianmingJiaocheng/js/reader.min.js
Java8JianmingJiaocheng/js/reader.min.map
Java8JianmingJiaocheng/js/hooks/__init__.py
Java8JianmingJiaocheng/js/hooks/extensions/__init__.py
Java8JianmingJiaocheng/js/hooks/extensions/highlight.js
Java8JianmingJiaocheng/js/libs/__init__.py
Java8JianmingJiaocheng/js/libs/jquery.min.js
Java8JianmingJiaocheng/js/libs/localforage.min.js
Java8JianmingJiaocheng/js/libs/screenfull.js
Java8JianmingJiaocheng/js/libs/screenfull.min.js
Java8JianmingJiaocheng/js/libs/zip.min.js
java8_jianming_jiaocheng-2024.3.2.0.dist-info/METADATA
java8_jianming_jiaocheng-2024.3.2.0.dist-info/WHEEL
java8_jianming_jiaocheng-2024.3.2.0.dist-info/entry_points.txt
java8_jianming_jiaocheng-2024.3.2.0.dist-info/top_level.txt
java8_jianming_jiaocheng-2024.3.2.0.dist-info/RECORD
